tests/__init__.py
tests/test_file.py
transcriptb2b/__init__.py
transcriptb2b/reverseTranscript/__init__.py
transcriptb2b/reverseTranscript/rna2dna.py
transcriptb2b/transcript/__init__.py
transcriptb2b/transcript/dna2rna.py
transcriptb2b-1.0.2.dist-info/METADATA
transcriptb2b-1.0.2.dist-info/WHEEL
transcriptb2b-1.0.2.dist-info/top_level.txt
transcriptb2b-1.0.2.dist-info/RECORD
