Metadata-Version: 2.1
Name: transcriptb2b
Version: 1.0.2
Summary: A small example package for transcripting DNA to RNA
Home-page: https://bitbucket.org/agdiaz/bioinformatics-102
Author: Bio2Byte
Author-email: jose.gavalda.garcia@vub.be
License: UNKNOWN
Project-URL: Bug Tracker, https://bitbucket.org/agdiaz/bioinformatics-102/issues
Platform: UNKNOWN
Classifier: Programming Language :: Python :: 3
Classifier: Operating System :: OS Independent
Requires-Python: >=3.6
